{
  "version": 1,
  "runs": [
    {
      "timestamp": "2026-04-24T15:01:39.740Z",
      "commit": "336fe6ec4dca760245c22251df1bbe02bb4199b0",
      "pages": {
        "/": {
          "performance": 69,
          "fcp": 4953,
          "lcp": 5034,
          "tbt": 0,
          "cls": 0
        },
        "/about": {
          "performance": 62,
          "fcp": 4936,
          "lcp": 11132,
          "tbt": 0,
          "cls": 0
        },
        "/services": {
          "performance": 66,
          "fcp": 5428,
          "lcp": 5505,
          "tbt": 0,
          "cls": 0
        },
        "/ma-portfolio": {
          "performance": 61,
          "fcp": 6559,
          "lcp": 6559,
          "tbt": 0,
          "cls": 0
        },
        "/brand": {
          "performance": 46,
          "fcp": 6216,
          "lcp": 6216,
          "tbt": 76,
          "cls": 0.336
        },
        "/hub": {
          "performance": 57,
          "fcp": 7816,
          "lcp": 10606,
          "tbt": 0,
          "cls": 0
        },
        "/hub/tools/tech-debt-calculator": {
          "performance": 57,
          "fcp": 8649,
          "lcp": 11584,
          "tbt": 0,
          "cls": 0
        },
        "/hub/tools/diligence-machine": {
          "performance": 68,
          "fcp": 5059,
          "lcp": 5067,
          "tbt": 5,
          "cls": 0
        },
        "/hub/tools/regulatory-map": {
          "performance": 56,
          "fcp": 9518,
          "lcp": 12450,
          "tbt": 55,
          "cls": 0
        },
        "/hub/tools/techpar": {
          "performance": 62,
          "fcp": 6296,
          "lcp": 6375,
          "tbt": 13,
          "cls": 0
        }
      }
    },
    {
      "timestamp": "2026-04-24T16:11:54.593Z",
      "commit": "e3fdd0f401f6bec4e50f6cad5565bbd68bfee398",
      "pages": {
        "/": {
          "performance": 68,
          "fcp": 5037,
          "lcp": 5194,
          "tbt": 0,
          "cls": 0
        },
        "/about": {
          "performance": 62,
          "fcp": 5055,
          "lcp": 11116,
          "tbt": 0,
          "cls": 0
        },
        "/services": {
          "performance": 57,
          "fcp": 8014,
          "lcp": 10969,
          "tbt": 0,
          "cls": 0
        },
        "/ma-portfolio": {
          "performance": 60,
          "fcp": 6851,
          "lcp": 7153,
          "tbt": 0,
          "cls": 0
        },
        "/brand": {
          "performance": 45,
          "fcp": 6368,
          "lcp": 6520,
          "tbt": 48,
          "cls": 0.336
        },
        "/hub": {
          "performance": 67,
          "fcp": 5172,
          "lcp": 5324,
          "tbt": 0,
          "cls": 0
        },
        "/hub/tools/tech-debt-calculator": {
          "performance": 57,
          "fcp": 8606,
          "lcp": 11539,
          "tbt": 0,
          "cls": 0
        },
        "/hub/tools/diligence-machine": {
          "performance": 65,
          "fcp": 5502,
          "lcp": 5654,
          "tbt": 8,
          "cls": 0
        },
        "/hub/tools/regulatory-map": {
          "performance": 56,
          "fcp": 9392,
          "lcp": 14082,
          "tbt": 55,
          "cls": 0
        },
        "/hub/tools/techpar": {
          "performance": 56,
          "fcp": 9040,
          "lcp": 11879,
          "tbt": 0,
          "cls": 0
        }
      }
    }
  ]
}
